{
  "collection_time": "2025-11-12T13:03:30.487419+05:45",
  "collection_time_npt": "2025-11-12 13:03:30 NPT",
  "day_of_week": "Wednesday",
  "market_schedule": "Wednesday - Trading Hours: 11:00 AM - 3:00 PM NPT",
  "total_records": 33789,
  "successful_endpoints": [
    "floorsheet",
    "price_volume",
    "live_market",
    "summary",
    "top_gainers",
    "top_losers",
    "nepse_index",
    "supply_demand"
  ],
  "records_by_source": {
    "floorsheet": 32957,
    "live_market": 303,
    "price_volume": 251,
    "top_losers": 179,
    "top_gainers": 96,
    "summary": 1,
    "nepse_index": 1,
    "supply_demand": 1
  },
  "filename": "nepse_cloud_20251112_130330.csv",
  "market_open": true,
  "collection_method": "cloud_automated"
}